README.md
setup.py
duet/__init__.py
duet_studio.egg-info/PKG-INFO
duet_studio.egg-info/SOURCES.txt
duet_studio.egg-info/dependency_links.txt
duet_studio.egg-info/top_level.txt