Metadata-Version: 2.1
Name: duet-studio
Version: 0.0.0
Summary: Web-based environment for writing lonestar code and viewing data
Home-page: UNKNOWN
Author: Jim Kitchen
Author-email: jim22k@gmail.com
License: UNKNOWN
Platform: UNKNOWN
Classifier: Programming Language :: Python :: 3
Classifier: Operating System :: OS Independent
